{
  "uuid": "list_layouts",
  "alias": "布局列表接口",
  "method": "GET",
  "request": {
    "query": [
      "page",
      "pageSize"
    ]
  },
  "blocks": [
    {
      "uuid": "starter",
      "nextBlock": "require_tenant_context"
    },
    {
      "uuid": "require_tenant_context",
      "alias": "读取当前企业",
      "functionName": "requireTenantContext",
      "inputs": { "datasource": "Mokelay" },
      "outputs": ["enterpriseUuid"],
      "nextBlock": "list_layouts_block"
    },
    {
      "uuid": "list_layouts_block",
      "alias": "布局分页 Block",
      "functionName": "page",
      "inputs": {
        "datasource": "Mokelay",
        "table": "layouts",
        "fields": [
          "uuid",
          "name",
          "layout_json",
          "created_at",
          "updated_at"
          ,"enterprise_uuid"
        ],
        "conditions": [{
          "group": false,
          "conditionType": "EQ",
          "fieldName": "enterprise_uuid",
          "fieldValue": { "template": "{{blocks['require_tenant_context'].outputs.enterpriseUuid}}" }
        }],
        "page": {
          "template": "{{request.query.page}}"
        },
        "pageSize": {
          "template": "{{request.query.pageSize}}"
        },
        "orderBy": [
          {
            "fieldName": "updated_at",
            "direction": "DESC"
          }
        ]
      },
      "outputs": [
        "datas",
        "total",
        "totalPages",
        "page",
        "pageSize",
        "hasPreviousPage",
        "hasNextPage"
      ],
      "nextBlock": null
    }
  ],
  "responses": {
    "list_layouts_block": {
      "layouts": {
        "template": "{{blocks['list_layouts_block'].outputs.datas}}"
      },
      "pagination": {
        "page": {
          "template": "{{blocks['list_layouts_block'].outputs.page}}"
        },
        "pageSize": {
          "template": "{{blocks['list_layouts_block'].outputs.pageSize}}"
        },
        "total": {
          "template": "{{blocks['list_layouts_block'].outputs.total}}"
        },
        "totalPages": {
          "template": "{{blocks['list_layouts_block'].outputs.totalPages}}"
        },
        "hasNextPage": {
          "template": "{{blocks['list_layouts_block'].outputs.hasNextPage}}"
        },
        "hasPreviousPage": {
          "template": "{{blocks['list_layouts_block'].outputs.hasPreviousPage}}"
        }
      }
    }
  }
}
